README
rdfxml.py
setup.py
rdf.plugins.parsers.rdfxml.egg-info/PKG-INFO
rdf.plugins.parsers.rdfxml.egg-info/SOURCES.txt
rdf.plugins.parsers.rdfxml.egg-info/dependency_links.txt
rdf.plugins.parsers.rdfxml.egg-info/requires.txt
rdf.plugins.parsers.rdfxml.egg-info/top_level.txt