Metadata-Version: 1.0
Name: rdf.plugins.parsers.rdfxml
Version: 0.9a1
Summary: An in-memory store plugin for `rdf`.
Home-page: http://rdflib.net/
Author: Daniel 'eikeon' Krech
Author-email: eikeon@eikeon.com
License: http://rdflib.net/latest/LICENSE
Platform: any
Classifier: Programming Language :: Python
Classifier: License :: OSI Approved :: BSD License
Classifier: Topic :: Software Development :: Libraries :: Python Modules
Classifier: Operating System :: OS Independent
Classifier: Natural Language :: English
